langchain_deepresearch/__init__.py
langchain_deepresearch/deep_researcher.py
langchain_deepresearch/services/__init__.py
langchain_deepresearch/services/deep_research_service.py
langchain_deepresearch/services/report_service.py
langchain_deepresearch/services/search_service.py
langchain_deepresearch/utils/__init__.py
langchain_deepresearch/utils/logging_utils.py
langchain_deepresearch-0.1.0.dist-info/METADATA
langchain_deepresearch-0.1.0.dist-info/WHEEL
langchain_deepresearch-0.1.0.dist-info/top_level.txt
langchain_deepresearch-0.1.0.dist-info/RECORD
