Metadata-Version: 2.2
Name: langchain-deepresearch
Version: 0.1.0
Summary: Autonomous research capabilities for LangChain models
Home-page: https://github.com/doganarif/langchain-deepresearch
Author: Arif Dogan
Author-email: me@arif.sh
Classifier: Programming Language :: Python :: 3
Classifier: Programming Language :: Python :: 3.9
Classifier: Programming Language :: Python :: 3.10
Classifier: Programming Language :: Python :: 3.11
Classifier: License :: OSI Approved :: MIT License
Classifier: Operating System :: OS Independent
Classifier: Development Status :: 3 - Alpha
Classifier: Intended Audience :: Science/Research
Classifier: Topic :: Scientific/Engineering :: Artificial Intelligence
Requires-Python: >=3.9
Requires-Dist: langchain-core>=0.1.0
Requires-Dist: aiohttp>=3.8.0
Requires-Dist: asyncio>=3.4.3
Requires-Dist: PyYAML>=6.0
Requires-Dist: requests>=2.0.0
Provides-Extra: openai
Requires-Dist: langchain-openai>=0.0.1; extra == "openai"
Provides-Extra: anthropic
Requires-Dist: langchain-anthropic>=0.0.1; extra == "anthropic"
Provides-Extra: google
Requires-Dist: langchain-google-genai>=0.0.1; extra == "google"
Provides-Extra: huggingface
Requires-Dist: langchain-huggingface>=0.0.1; extra == "huggingface"
Provides-Extra: all
Requires-Dist: langchain-openai>=0.0.1; extra == "all"
Requires-Dist: langchain-anthropic>=0.0.1; extra == "all"
Requires-Dist: langchain-google-genai>=0.0.1; extra == "all"
Requires-Dist: langchain-huggingface>=0.0.1; extra == "all"
Dynamic: author
Dynamic: author-email
Dynamic: classifier
Dynamic: description
Dynamic: description-content-type
Dynamic: home-page
Dynamic: provides-extra
Dynamic: requires-dist
Dynamic: requires-python
Dynamic: summary
